[
  {
    "Type": "DataTable",
    "Name": "GOP_Event_Mercado",
    "Class": "UScriptClass'DataTable'",
    "Flags": "RF_Public | RF_Standalone | RF_Transactional | RF_WasLoaded | RF_LoadCompleted",
    "Properties": {
      "RowStruct": {
        "ObjectName": "ScriptStruct'GOP_Event_CommonTable'",
        "ObjectPath": "/Script/Nicola"
      }
    },
    "Rows": {
      "EVENT_Mercado_MAPLIST_C11F0101_0": {
        "SelfId": "EVENT_Mercado_MAPLIST_C11F0101_0",
        "EventID": "Mercado_Out_SUB_0_SCENE_0010_010",
        "TriggerType": "EEventTriggerType::SCENE",
        "TriggerID": "MAPLIST_C11F0101",
        "EventPriority": 0,
        "ProgressLower": 0,
        "ProgressUpper": 30,
        "StartFlagName1": "None",
        "IsTrueCondition1": false,
        "IsAndOperation": false,
        "StartFlagName2": "None",
        "IsTrueCondition2": false,
        "ScenarioProgress": 0
      },
      "EVENT_Mercado_Mercado_Out_Guard_01_L3_1": {
        "SelfId": "EVENT_Mercado_Mercado_Out_Guard_01_L3_1",
        "EventID": "Mercado_Out_SUB_0_ACTOR_0120_010",
        "TriggerType": "EEventTriggerType::ACTOR",
        "TriggerID": "Mercado_Out_Guard_01_L3",
        "EventPriority": 1,
        "ProgressLower": 0,
        "ProgressUpper": 30,
        "StartFlagName1": "None",
        "IsTrueCondition1": false,
        "IsAndOperation": false,
        "StartFlagName2": "None",
        "IsTrueCondition2": false,
        "ScenarioProgress": 0
      },
      "EVENT_Mercado_Mercado_Out_Guard_01_L1_0": {
        "SelfId": "EVENT_Mercado_Mercado_Out_Guard_01_L1_0",
        "EventID": "Mercado_Out_SUB_0_ACTOR_0110_010",
        "TriggerType": "EEventTriggerType::ACTOR",
        "TriggerID": "Mercado_Out_Guard_01_L1",
        "EventPriority": 0,
        "ProgressLower": 0,
        "ProgressUpper": 30,
        "StartFlagName1": "FE91",
        "IsTrueCondition1": true,
        "IsAndOperation": false,
        "StartFlagName2": "None",
        "IsTrueCondition2": false,
        "ScenarioProgress": 0
      },
      "EVENT_Mercado_Mercado_Out_Merchant_01_L3_1": {
        "SelfId": "EVENT_Mercado_Mercado_Out_Merchant_01_L3_1",
        "EventID": "Mercado_Out_SUB_0_ACTOR_0220_010",
        "TriggerType": "EEventTriggerType::ACTOR",
        "TriggerID": "Mercado_Out_Merchant_01_L3",
        "EventPriority": 1,
        "ProgressLower": 0,
        "ProgressUpper": 30,
        "StartFlagName1": "None",
        "IsTrueCondition1": false,
        "IsAndOperation": false,
        "StartFlagName2": "None",
        "IsTrueCondition2": false,
        "ScenarioProgress": 0
      },
      "EVENT_Mercado_Mercado_Out_Merchant_01_L1_0": {
        "SelfId": "EVENT_Mercado_Mercado_Out_Merchant_01_L1_0",
        "EventID": "Mercado_Out_SUB_0_ACTOR_0210_010",
        "TriggerType": "EEventTriggerType::ACTOR",
        "TriggerID": "Mercado_Out_Merchant_01_L1",
        "EventPriority": 0,
        "ProgressLower": 0,
        "ProgressUpper": 30,
        "StartFlagName1": "FE91",
        "IsTrueCondition1": true,
        "IsAndOperation": false,
        "StartFlagName2": "None",
        "IsTrueCondition2": false,
        "ScenarioProgress": 0
      },
      "EVENT_Mercado_Mercado_Out_Guard_02_L3_1": {
        "SelfId": "EVENT_Mercado_Mercado_Out_Guard_02_L3_1",
        "EventID": "Mercado_Out_SUB_0_ACTOR_0320_010",
        "TriggerType": "EEventTriggerType::ACTOR",
        "TriggerID": "Mercado_Out_Guard_02_L3",
        "EventPriority": 1,
        "ProgressLower": 0,
        "ProgressUpper": 30,
        "StartFlagName1": "None",
        "IsTrueCondition1": false,
        "IsAndOperation": false,
        "StartFlagName2": "None",
        "IsTrueCondition2": false,
        "ScenarioProgress": 0
      },
      "EVENT_Mercado_Mercado_Out_Guard_02_L1_0": {
        "SelfId": "EVENT_Mercado_Mercado_Out_Guard_02_L1_0",
        "EventID": "Mercado_Out_SUB_0_ACTOR_0310_010",
        "TriggerType": "EEventTriggerType::ACTOR",
        "TriggerID": "Mercado_Out_Guard_02_L1",
        "EventPriority": 0,
        "ProgressLower": 0,
        "ProgressUpper": 30,
        "StartFlagName1": "FE91",
        "IsTrueCondition1": true,
        "IsAndOperation": false,
        "StartFlagName2": "None",
        "IsTrueCondition2": false,
        "ScenarioProgress": 0
      },
      "EVENT_Mercado_Mercado_Out_Man_01_L3_1": {
        "SelfId": "EVENT_Mercado_Mercado_Out_Man_01_L3_1",
        "EventID": "Mercado_Out_SUB_0_ACTOR_0420_010",
        "TriggerType": "EEventTriggerType::ACTOR",
        "TriggerID": "Mercado_Out_Man_01_L3",
        "EventPriority": 1,
        "ProgressLower": 0,
        "ProgressUpper": 30,
        "StartFlagName1": "None",
        "IsTrueCondition1": false,
        "IsAndOperation": false,
        "StartFlagName2": "None",
        "IsTrueCondition2": false,
        "ScenarioProgress": 0
      },
      "EVENT_Mercado_Mercado_Out_Man_01_L1_0": {
        "SelfId": "EVENT_Mercado_Mercado_Out_Man_01_L1_0",
        "EventID": "Mercado_Out_SUB_0_ACTOR_0410_010",
        "TriggerType": "EEventTriggerType::ACTOR",
        "TriggerID": "Mercado_Out_Man_01_L1",
        "EventPriority": 0,
        "ProgressLower": 0,
        "ProgressUpper": 30,
        "StartFlagName1": "FE91",
        "IsTrueCondition1": true,
        "IsAndOperation": false,
        "StartFlagName2": "None",
        "IsTrueCondition2": false,
        "ScenarioProgress": 0
      },
      "EVENT_Mercado_Mercado_Out_Man_02_L1_0": {
        "SelfId": "EVENT_Mercado_Mercado_Out_Man_02_L1_0",
        "EventID": "Mercado_Out_SUB_0_ACTOR_0410_020",
        "TriggerType": "EEventTriggerType::ACTOR",
        "TriggerID": "Mercado_Out_Man_02_L1",
        "EventPriority": 0,
        "ProgressLower": 0,
        "ProgressUpper": 30,
        "StartFlagName1": "FE91",
        "IsTrueCondition1": true,
        "IsAndOperation": false,
        "StartFlagName2": "None",
        "IsTrueCondition2": false,
        "ScenarioProgress": 0
      },
      "EVENT_Mercado_Mercado_Out_Minister_01_L3_1": {
        "SelfId": "EVENT_Mercado_Mercado_Out_Minister_01_L3_1",
        "EventID": "Mercado_Out_SUB_0_ACTOR_0520_010",
        "TriggerType": "EEventTriggerType::ACTOR",
        "TriggerID": "Mercado_Out_Minister_01_L3",
        "EventPriority": 1,
        "ProgressLower": 0,
        "ProgressUpper": 30,
        "StartFlagName1": "None",
        "IsTrueCondition1": false,
        "IsAndOperation": false,
        "StartFlagName2": "None",
        "IsTrueCondition2": false,
        "ScenarioProgress": 0
      },
      "EVENT_Mercado_Mercado_Out_Minister_01_L1_0": {
        "SelfId": "EVENT_Mercado_Mercado_Out_Minister_01_L1_0",
        "EventID": "Mercado_Out_SUB_0_ACTOR_0510_010",
        "TriggerType": "EEventTriggerType::ACTOR",
        "TriggerID": "Mercado_Out_Minister_01_L1",
        "EventPriority": 0,
        "ProgressLower": 0,
        "ProgressUpper": 30,
        "StartFlagName1": "FE91",
        "IsTrueCondition1": true,
        "IsAndOperation": false,
        "StartFlagName2": "None",
        "IsTrueCondition2": false,
        "ScenarioProgress": 0
      },
      "EVENT_Mercado_Mercado_Out_Abbot_Dharma_01_L3_1": {
        "SelfId": "EVENT_Mercado_Mercado_Out_Abbot_Dharma_01_L3_1",
        "EventID": "Mercado_Out_SUB_0_ACTOR_0620_010",
        "TriggerType": "EEventTriggerType::ACTOR",
        "TriggerID": "Mercado_Out_Abbot_Dharma_01_L3",
        "EventPriority": 1,
        "ProgressLower": 0,
        "ProgressUpper": 30,
        "StartFlagName1": "None",
        "IsTrueCondition1": false,
        "IsAndOperation": false,
        "StartFlagName2": "None",
        "IsTrueCondition2": false,
        "ScenarioProgress": 0
      },
      "EVENT_Mercado_Mercado_Out_Abbot_Dharma_01_L1_0": {
        "SelfId": "EVENT_Mercado_Mercado_Out_Abbot_Dharma_01_L1_0",
        "EventID": "Mercado_Out_SUB_0_ACTOR_0610_010",
        "TriggerType": "EEventTriggerType::ACTOR",
        "TriggerID": "Mercado_Out_Abbot_Dharma_01_L1",
        "EventPriority": 0,
        "ProgressLower": 0,
        "ProgressUpper": 30,
        "StartFlagName1": "FE91",
        "IsTrueCondition1": true,
        "IsAndOperation": false,
        "StartFlagName2": "None",
        "IsTrueCondition2": false,
        "ScenarioProgress": 0
      },
      "EVENT_Mercado_Mercado_Out_MINIDEMON_00_L3_0": {
        "SelfId": "EVENT_Mercado_Mercado_Out_MINIDEMON_00_L3_0",
        "EventID": "Mercado_Out_SUB_0_MBR_SCOUT_0710_010",
        "TriggerType": "EEventTriggerType::MBR_SCOUT",
        "TriggerID": "Mercado_Out_MINIDEMON_00_L3",
        "EventPriority": 0,
        "ProgressLower": 0,
        "ProgressUpper": 30,
        "StartFlagName1": "None",
        "IsTrueCondition1": false,
        "IsAndOperation": false,
        "StartFlagName2": "None",
        "IsTrueCondition2": false,
        "ScenarioProgress": 0
      },
      "EVENT_Mercado_Mercado_Out_Priest_01_L3_0": {
        "SelfId": "EVENT_Mercado_Mercado_Out_Priest_01_L3_0",
        "EventID": "Mercado_Out_SUB_0_ACTOR_0820_010",
        "TriggerType": "EEventTriggerType::ACTOR",
        "TriggerID": "Mercado_Out_Priest_01_L3",
        "EventPriority": 0,
        "ProgressLower": 0,
        "ProgressUpper": 30,
        "StartFlagName1": "None",
        "IsTrueCondition1": false,
        "IsAndOperation": false,
        "StartFlagName2": "None",
        "IsTrueCondition2": false,
        "ScenarioProgress": 0
      },
      "EVENT_Mercado_Mercado_Out_Priest_01_L1_0": {
        "SelfId": "EVENT_Mercado_Mercado_Out_Priest_01_L1_0",
        "EventID": "Mercado_Out_SUB_0_ACTOR_0810_010",
        "TriggerType": "EEventTriggerType::ACTOR",
        "TriggerID": "Mercado_Out_Priest_01_L1",
        "EventPriority": 0,
        "ProgressLower": 0,
        "ProgressUpper": 30,
        "StartFlagName1": "FE91",
        "IsTrueCondition1": true,
        "IsAndOperation": false,
        "StartFlagName2": "None",
        "IsTrueCondition2": false,
        "ScenarioProgress": 0
      },
      "EVENT_Mercado_Mercado_Shop02_2F_Scholar_01_L3_1": {
        "SelfId": "EVENT_Mercado_Mercado_Shop02_2F_Scholar_01_L3_1",
        "EventID": "Mercado_Shop02_SUB_0_ACTOR_0120_010",
        "TriggerType": "EEventTriggerType::ACTOR",
        "TriggerID": "Mercado_Shop02_2F_Scholar_01_L3",
        "EventPriority": 1,
        "ProgressLower": 0,
        "ProgressUpper": 30,
        "StartFlagName1": "None",
        "IsTrueCondition1": false,
        "IsAndOperation": false,
        "StartFlagName2": "None",
        "IsTrueCondition2": false,
        "ScenarioProgress": 0
      },
      "EVENT_Mercado_Mercado_Shop02_2F_Scholar_01_L1_0": {
        "SelfId": "EVENT_Mercado_Mercado_Shop02_2F_Scholar_01_L1_0",
        "EventID": "Mercado_Shop02_SUB_0_ACTOR_0110_010",
        "TriggerType": "EEventTriggerType::ACTOR",
        "TriggerID": "Mercado_Shop02_2F_Scholar_01_L1",
        "EventPriority": 0,
        "ProgressLower": 0,
        "ProgressUpper": 30,
        "StartFlagName1": "FE91",
        "IsTrueCondition1": true,
        "IsAndOperation": false,
        "StartFlagName2": "None",
        "IsTrueCondition2": false,
        "ScenarioProgress": 0
      },
      "EVENT_Mercado_Mercado_Shop02_2F_Uncle_01_L3_1": {
        "SelfId": "EVENT_Mercado_Mercado_Shop02_2F_Uncle_01_L3_1",
        "EventID": "Mercado_Shop02_SUB_0_ACTOR_0220_010",
        "TriggerType": "EEventTriggerType::ACTOR",
        "TriggerID": "Mercado_Shop02_2F_Uncle_01_L3",
        "EventPriority": 1,
        "ProgressLower": 0,
        "ProgressUpper": 30,
        "StartFlagName1": "None",
        "IsTrueCondition1": false,
        "IsAndOperation": false,
        "StartFlagName2": "None",
        "IsTrueCondition2": false,
        "ScenarioProgress": 0
      },
      "EVENT_Mercado_Mercado_Shop02_2F_Uncle_01_L1_0": {
        "SelfId": "EVENT_Mercado_Mercado_Shop02_2F_Uncle_01_L1_0",
        "EventID": "Mercado_Shop02_SUB_0_ACTOR_0210_010",
        "TriggerType": "EEventTriggerType::ACTOR",
        "TriggerID": "Mercado_Shop02_2F_Uncle_01_L1",
        "EventPriority": 0,
        "ProgressLower": 0,
        "ProgressUpper": 30,
        "StartFlagName1": "FE91",
        "IsTrueCondition1": true,
        "IsAndOperation": false,
        "StartFlagName2": "None",
        "IsTrueCondition2": false,
        "ScenarioProgress": 0
      },
      "EVENT_Mercado_Mercado_Shop02_2F_Woman_01_L3_1": {
        "SelfId": "EVENT_Mercado_Mercado_Shop02_2F_Woman_01_L3_1",
        "EventID": "Mercado_Shop02_SUB_0_ACTOR_0320_010",
        "TriggerType": "EEventTriggerType::ACTOR",
        "TriggerID": "Mercado_Shop02_2F_Woman_01_L3",
        "EventPriority": 1,
        "ProgressLower": 0,
        "ProgressUpper": 30,
        "StartFlagName1": "None",
        "IsTrueCondition1": false,
        "IsAndOperation": false,
        "StartFlagName2": "None",
        "IsTrueCondition2": false,
        "ScenarioProgress": 0
      },
      "EVENT_Mercado_Mercado_Shop02_2F_Woman_01_L1_0": {
        "SelfId": "EVENT_Mercado_Mercado_Shop02_2F_Woman_01_L1_0",
        "EventID": "Mercado_Shop02_SUB_0_ACTOR_0310_010",
        "TriggerType": "EEventTriggerType::ACTOR",
        "TriggerID": "Mercado_Shop02_2F_Woman_01_L1",
        "EventPriority": 0,
        "ProgressLower": 0,
        "ProgressUpper": 30,
        "StartFlagName1": "FE91",
        "IsTrueCondition1": true,
        "IsAndOperation": false,
        "StartFlagName2": "None",
        "IsTrueCondition2": false,
        "ScenarioProgress": 0
      },
      "EVENT_Mercado_Mercado_Shop02_2F_Boy_01_L3_1": {
        "SelfId": "EVENT_Mercado_Mercado_Shop02_2F_Boy_01_L3_1",
        "EventID": "Mercado_Shop02_SUB_0_ACTOR_0420_010",
        "TriggerType": "EEventTriggerType::ACTOR",
        "TriggerID": "Mercado_Shop02_2F_Boy_01_L3",
        "EventPriority": 1,
        "ProgressLower": 0,
        "ProgressUpper": 30,
        "StartFlagName1": "None",
        "IsTrueCondition1": false,
        "IsAndOperation": false,
        "StartFlagName2": "None",
        "IsTrueCondition2": false,
        "ScenarioProgress": 0
      },
      "EVENT_Mercado_Mercado_Shop02_2F_Boy_01_L1_0": {
        "SelfId": "EVENT_Mercado_Mercado_Shop02_2F_Boy_01_L1_0",
        "EventID": "Mercado_Shop02_SUB_0_ACTOR_0410_010",
        "TriggerType": "EEventTriggerType::ACTOR",
        "TriggerID": "Mercado_Shop02_2F_Boy_01_L1",
        "EventPriority": 0,
        "ProgressLower": 0,
        "ProgressUpper": 30,
        "StartFlagName1": "FE91",
        "IsTrueCondition1": true,
        "IsAndOperation": false,
        "StartFlagName2": "None",
        "IsTrueCondition2": false,
        "ScenarioProgress": 0
      },
      "EVENT_Mercado_Mercado_Hotel_Merchant_01_L3_1": {
        "SelfId": "EVENT_Mercado_Mercado_Hotel_Merchant_01_L3_1",
        "EventID": "Mercado_Hotel_SUB_0_ACTOR_0120_010",
        "TriggerType": "EEventTriggerType::ACTOR",
        "TriggerID": "Mercado_Hotel_Merchant_01_L3",
        "EventPriority": 1,
        "ProgressLower": 0,
        "ProgressUpper": 30,
        "StartFlagName1": "None",
        "IsTrueCondition1": false,
        "IsAndOperation": false,
        "StartFlagName2": "None",
        "IsTrueCondition2": false,
        "ScenarioProgress": 0
      },
      "EVENT_Mercado_Mercado_Hotel_Merchant_01_L1_0": {
        "SelfId": "EVENT_Mercado_Mercado_Hotel_Merchant_01_L1_0",
        "EventID": "Mercado_Hotel_SUB_0_ACTOR_0110_010",
        "TriggerType": "EEventTriggerType::ACTOR",
        "TriggerID": "Mercado_Hotel_Merchant_01_L1",
        "EventPriority": 0,
        "ProgressLower": 0,
        "ProgressUpper": 30,
        "StartFlagName1": "FE91",
        "IsTrueCondition1": true,
        "IsAndOperation": false,
        "StartFlagName2": "None",
        "IsTrueCondition2": false,
        "ScenarioProgress": 0
      },
      "EVENT_Mercado_Mercado_Hotel_Garai_01_L3_1": {
        "SelfId": "EVENT_Mercado_Mercado_Hotel_Garai_01_L3_1",
        "EventID": "Mercado_Hotel_SUB_0_ACTOR_0220_010",
        "TriggerType": "EEventTriggerType::ACTOR",
        "TriggerID": "Mercado_Hotel_Garai_01_L3",
        "EventPriority": 1,
        "ProgressLower": 0,
        "ProgressUpper": 30,
        "StartFlagName1": "None",
        "IsTrueCondition1": false,
        "IsAndOperation": false,
        "StartFlagName2": "None",
        "IsTrueCondition2": false,
        "ScenarioProgress": 0
      },
      "EVENT_Mercado_Mercado_Hotel_Garai_01_L1_0": {
        "SelfId": "EVENT_Mercado_Mercado_Hotel_Garai_01_L1_0",
        "EventID": "Mercado_Hotel_SUB_0_ACTOR_0210_010",
        "TriggerType": "EEventTriggerType::ACTOR",
        "TriggerID": "Mercado_Hotel_Garai_01_L1",
        "EventPriority": 0,
        "ProgressLower": 0,
        "ProgressUpper": 30,
        "StartFlagName1": "FE91",
        "IsTrueCondition1": true,
        "IsAndOperation": false,
        "StartFlagName2": "None",
        "IsTrueCondition2": false,
        "ScenarioProgress": 0
      },
      "EVENT_Mercado_MAPLIST_C11R0402_1": {
        "SelfId": "EVENT_Mercado_MAPLIST_C11R0402_1",
        "EventID": "Mercado_BattleRoad_SUB_0_SCENE_0010_010",
        "TriggerType": "EEventTriggerType::SCENE",
        "TriggerID": "MAPLIST_C11R0402",
        "EventPriority": 1,
        "ProgressLower": 0,
        "ProgressUpper": 30,
        "StartFlagName1": "FE960",
        "IsTrueCondition1": false,
        "IsAndOperation": false,
        "StartFlagName2": "None",
        "IsTrueCondition2": false,
        "ScenarioProgress": 0
      },
      "EVENT_Mercado_ARankMaster_01_L1_0": {
        "SelfId": "EVENT_Mercado_ARankMaster_01_L1_0",
        "EventID": "Mercado_BattleRoad_Arena_SUB_0_SCENE_0110_010",
        "TriggerType": "EEventTriggerType::ACTOR",
        "TriggerID": "ARankMaster_01_L1",
        "EventPriority": 0,
        "ProgressLower": 0,
        "ProgressUpper": 30,
        "StartFlagName1": "None",
        "IsTrueCondition1": false,
        "IsAndOperation": false,
        "StartFlagName2": "None",
        "IsTrueCondition2": false,
        "ScenarioProgress": 0
      },
      "EVENT_Mercado_ARankMaster_01_L3_0": {
        "SelfId": "EVENT_Mercado_ARankMaster_01_L3_0",
        "EventID": "Mercado_BattleRoad_Arena_SUB_0_SCENE_0110_010",
        "TriggerType": "EEventTriggerType::ACTOR",
        "TriggerID": "ARankMaster_01_L3",
        "EventPriority": 0,
        "ProgressLower": 0,
        "ProgressUpper": 30,
        "StartFlagName1": "None",
        "IsTrueCondition1": false,
        "IsAndOperation": false,
        "StartFlagName2": "None",
        "IsTrueCondition2": false,
        "ScenarioProgress": 0
      },
      "EVENT_Mercado_Mercado_MBR_Info_01_L1_0": {
        "SelfId": "EVENT_Mercado_Mercado_MBR_Info_01_L1_0",
        "EventID": "Mercado_BattleRoad_Info_SUB_0_ACTOR_0110_010",
        "TriggerType": "EEventTriggerType::ACTOR",
        "TriggerID": "Mercado_MBR_Info_01_L1",
        "EventPriority": 0,
        "ProgressLower": 0,
        "ProgressUpper": 30,
        "StartFlagName1": "None",
        "IsTrueCondition1": false,
        "IsAndOperation": false,
        "StartFlagName2": "None",
        "IsTrueCondition2": false,
        "ScenarioProgress": 0
      },
      "EVENT_Mercado_Mercado_MBR_Info_01_L3_0": {
        "SelfId": "EVENT_Mercado_Mercado_MBR_Info_01_L3_0",
        "EventID": "Mercado_BattleRoad_Info_SUB_0_ACTOR_0110_010",
        "TriggerType": "EEventTriggerType::ACTOR",
        "TriggerID": "Mercado_MBR_Info_01_L3",
        "EventPriority": 0,
        "ProgressLower": 0,
        "ProgressUpper": 30,
        "StartFlagName1": "None",
        "IsTrueCondition1": false,
        "IsAndOperation": false,
        "StartFlagName2": "None",
        "IsTrueCondition2": false,
        "ScenarioProgress": 0
      },
      "EVENT_Mercado_Mercado_MBR_Zoo_01_L1_0": {
        "SelfId": "EVENT_Mercado_Mercado_MBR_Zoo_01_L1_0",
        "EventID": "Mercado_BattleRoad_Zoo_SUB_0_ACTOR_0110_010",
        "TriggerType": "EEventTriggerType::ACTOR",
        "TriggerID": "Mercado_MBR_Zoo_01_L1",
        "EventPriority": 0,
        "ProgressLower": 0,
        "ProgressUpper": 30,
        "StartFlagName1": "None",
        "IsTrueCondition1": false,
        "IsAndOperation": false,
        "StartFlagName2": "None",
        "IsTrueCondition2": false,
        "ScenarioProgress": 0
      },
      "EVENT_Mercado_Mercado_MBR_Zoo_01_L3_0": {
        "SelfId": "EVENT_Mercado_Mercado_MBR_Zoo_01_L3_0",
        "EventID": "Mercado_BattleRoad_Zoo_SUB_0_ACTOR_0110_010",
        "TriggerType": "EEventTriggerType::ACTOR",
        "TriggerID": "Mercado_MBR_Zoo_01_L3",
        "EventPriority": 0,
        "ProgressLower": 0,
        "ProgressUpper": 30,
        "StartFlagName1": "None",
        "IsTrueCondition1": false,
        "IsAndOperation": false,
        "StartFlagName2": "None",
        "IsTrueCondition2": false,
        "ScenarioProgress": 0
      },
      "EVENT_Mercado_Mercado_MBR_Entry_01_L1_0": {
        "SelfId": "EVENT_Mercado_Mercado_MBR_Entry_01_L1_0",
        "EventID": "Mercado_BattleRoad_Entry_SUB_0_ACTOR_0110_010",
        "TriggerType": "EEventTriggerType::ACTOR",
        "TriggerID": "Mercado_MBR_Entry_01_L1",
        "EventPriority": 0,
        "ProgressLower": 0,
        "ProgressUpper": 30,
        "StartFlagName1": "None",
        "IsTrueCondition1": false,
        "IsAndOperation": false,
        "StartFlagName2": "None",
        "IsTrueCondition2": false,
        "ScenarioProgress": 0
      },
      "EVENT_Mercado_Mercado_MBR_Entry_01_L3_0": {
        "SelfId": "EVENT_Mercado_Mercado_MBR_Entry_01_L3_0",
        "EventID": "Mercado_BattleRoad_Entry_SUB_0_ACTOR_0110_010",
        "TriggerType": "EEventTriggerType::ACTOR",
        "TriggerID": "Mercado_MBR_Entry_01_L3",
        "EventPriority": 0,
        "ProgressLower": 0,
        "ProgressUpper": 30,
        "StartFlagName1": "None",
        "IsTrueCondition1": false,
        "IsAndOperation": false,
        "StartFlagName2": "None",
        "IsTrueCondition2": false,
        "ScenarioProgress": 0
      },
      "EVENT_Mercado_MAPLIST_C11R0402_0": {
        "SelfId": "EVENT_Mercado_MAPLIST_C11R0402_0",
        "EventID": "Mercado_BattleRoad_Entry_SUB_0_SCENE_0110_010",
        "TriggerType": "EEventTriggerType::SCENE",
        "TriggerID": "MAPLIST_C11R0402",
        "EventPriority": 0,
        "ProgressLower": 0,
        "ProgressUpper": 30,
        "StartFlagName1": "FE850",
        "IsTrueCondition1": true,
        "IsAndOperation": false,
        "StartFlagName2": "None",
        "IsTrueCondition2": false,
        "ScenarioProgress": 0
      },
      "EVENT_Mercado_Mercado_MBR_Nun_01_L1_0": {
        "SelfId": "EVENT_Mercado_Mercado_MBR_Nun_01_L1_0",
        "EventID": "Mercado_BattleRoad_Nun_SUB_0_ACTOR_0110_010",
        "TriggerType": "EEventTriggerType::ACTOR",
        "TriggerID": "Mercado_MBR_Nun_01_L1",
        "EventPriority": 0,
        "ProgressLower": 0,
        "ProgressUpper": 30,
        "StartFlagName1": "None",
        "IsTrueCondition1": false,
        "IsAndOperation": false,
        "StartFlagName2": "None",
        "IsTrueCondition2": false,
        "ScenarioProgress": 0
      },
      "EVENT_Mercado_Mercado_MBR_Nun_01_L3_0": {
        "SelfId": "EVENT_Mercado_Mercado_MBR_Nun_01_L3_0",
        "EventID": "Mercado_BattleRoad_Nun_SUB_0_ACTOR_0110_010",
        "TriggerType": "EEventTriggerType::ACTOR",
        "TriggerID": "Mercado_MBR_Nun_01_L3",
        "EventPriority": 0,
        "ProgressLower": 0,
        "ProgressUpper": 30,
        "StartFlagName1": "None",
        "IsTrueCondition1": false,
        "IsAndOperation": false,
        "StartFlagName2": "None",
        "IsTrueCondition2": false,
        "ScenarioProgress": 0
      },
      "EVENT_Mercado_Mercado_MBR_Bank_01_L1_0": {
        "SelfId": "EVENT_Mercado_Mercado_MBR_Bank_01_L1_0",
        "EventID": "Mercado_BattleRoad_Bank_SUB_0_ACTOR_0110_010",
        "TriggerType": "EEventTriggerType::ACTOR",
        "TriggerID": "Mercado_MBR_Bank_01_L1",
        "EventPriority": 0,
        "ProgressLower": 0,
        "ProgressUpper": 30,
        "StartFlagName1": "None",
        "IsTrueCondition1": false,
        "IsAndOperation": false,
        "StartFlagName2": "None",
        "IsTrueCondition2": false,
        "ScenarioProgress": 0
      },
      "EVENT_Mercado_Mercado_MBR_Bank_01_L3_0": {
        "SelfId": "EVENT_Mercado_Mercado_MBR_Bank_01_L3_0",
        "EventID": "Mercado_BattleRoad_Bank_SUB_0_ACTOR_0110_010",
        "TriggerType": "EEventTriggerType::ACTOR",
        "TriggerID": "Mercado_MBR_Bank_01_L3",
        "EventPriority": 0,
        "ProgressLower": 0,
        "ProgressUpper": 30,
        "StartFlagName1": "None",
        "IsTrueCondition1": false,
        "IsAndOperation": false,
        "StartFlagName2": "None",
        "IsTrueCondition2": false,
        "ScenarioProgress": 0
      },
      "EVENT_Mercado_Mercado_BattleRoad_Slime_01_L1_0": {
        "SelfId": "EVENT_Mercado_Mercado_BattleRoad_Slime_01_L1_0",
        "EventID": "Mercado_BattleRoad_Slime_SUB_0_ACTOR_0110_010",
        "TriggerType": "EEventTriggerType::ACTOR",
        "TriggerID": "Mercado_BattleRoad_Slime_01_L1",
        "EventPriority": 0,
        "ProgressLower": 0,
        "ProgressUpper": 30,
        "StartFlagName1": "None",
        "IsTrueCondition1": false,
        "IsAndOperation": false,
        "StartFlagName2": "None",
        "IsTrueCondition2": false,
        "ScenarioProgress": 0
      },
      "EVENT_Mercado_Mercado_BattleRoad_Slime_01_L3_0": {
        "SelfId": "EVENT_Mercado_Mercado_BattleRoad_Slime_01_L3_0",
        "EventID": "Mercado_BattleRoad_Slime_SUB_0_ACTOR_0110_010",
        "TriggerType": "EEventTriggerType::ACTOR",
        "TriggerID": "Mercado_BattleRoad_Slime_01_L3",
        "EventPriority": 0,
        "ProgressLower": 0,
        "ProgressUpper": 30,
        "StartFlagName1": "None",
        "IsTrueCondition1": false,
        "IsAndOperation": false,
        "StartFlagName2": "None",
        "IsTrueCondition2": false,
        "ScenarioProgress": 0
      },
      "EVENT_Mercado_MAPLIST_C11R0403_0": {
        "SelfId": "EVENT_Mercado_MAPLIST_C11R0403_0",
        "EventID": "Mercado_BattleRoad_Arena_SUB_0_SCENE_0110_010",
        "TriggerType": "EEventTriggerType::SCENE",
        "TriggerID": "MAPLIST_C11R0403",
        "EventPriority": 0,
        "ProgressLower": 0,
        "ProgressUpper": 30,
        "StartFlagName1": "None",
        "IsTrueCondition1": false,
        "IsAndOperation": false,
        "StartFlagName2": "None",
        "IsTrueCondition2": false,
        "ScenarioProgress": 0
      },
      "EVENT_Mercado_MBR_Rank_S_0": {
        "SelfId": "EVENT_Mercado_MBR_Rank_S_0",
        "EventID": "Mercado_BattleRoad_Arena_SUB_0_BATTLE_END_0110_010",
        "TriggerType": "EEventTriggerType::BATTLE_END",
        "TriggerID": "MBR_Rank_S",
        "EventPriority": 0,
        "ProgressLower": 0,
        "ProgressUpper": 30,
        "StartFlagName1": "None",
        "IsTrueCondition1": false,
        "IsAndOperation": false,
        "StartFlagName2": "None",
        "IsTrueCondition2": false,
        "ScenarioProgress": 0
      },
      "EVENT_Mercado_MBR_Rank_A_0": {
        "SelfId": "EVENT_Mercado_MBR_Rank_A_0",
        "EventID": "Mercado_BattleRoad_Arena_SUB_0_BATTLE_END_0210_010",
        "TriggerType": "EEventTriggerType::BATTLE_END",
        "TriggerID": "MBR_Rank_A",
        "EventPriority": 0,
        "ProgressLower": 0,
        "ProgressUpper": 30,
        "StartFlagName1": "None",
        "IsTrueCondition1": false,
        "IsAndOperation": false,
        "StartFlagName2": "None",
        "IsTrueCondition2": false,
        "ScenarioProgress": 0
      },
      "EVENT_Mercado_Mercado_MBR_Arakure_01_L3_0": {
        "SelfId": "EVENT_Mercado_Mercado_MBR_Arakure_01_L3_0",
        "EventID": "Mercado_BattleRoad_SUB_0_ACTOR_0110_010",
        "TriggerType": "EEventTriggerType::ACTOR",
        "TriggerID": "Mercado_MBR_Arakure_01_L3",
        "EventPriority": 0,
        "ProgressLower": 0,
        "ProgressUpper": 30,
        "StartFlagName1": "None",
        "IsTrueCondition1": false,
        "IsAndOperation": false,
        "StartFlagName2": "None",
        "IsTrueCondition2": false,
        "ScenarioProgress": 0
      },
      "EVENT_Mercado_Mercado_MBR_BunnyGirl_03_L3_0": {
        "SelfId": "EVENT_Mercado_Mercado_MBR_BunnyGirl_03_L3_0",
        "EventID": "Mercado_BattleRoad_SUB_0_ACTOR_0210_010",
        "TriggerType": "EEventTriggerType::ACTOR",
        "TriggerID": "Mercado_MBR_BunnyGirl_03_L3",
        "EventPriority": 0,
        "ProgressLower": 0,
        "ProgressUpper": 30,
        "StartFlagName1": "None",
        "IsTrueCondition1": false,
        "IsAndOperation": false,
        "StartFlagName2": "None",
        "IsTrueCondition2": false,
        "ScenarioProgress": 0
      },
      "EVENT_Mercado_Mercado_MBR_Girl_01_L3_0": {
        "SelfId": "EVENT_Mercado_Mercado_MBR_Girl_01_L3_0",
        "EventID": "Mercado_BattleRoad_SUB_0_ACTOR_0310_010",
        "TriggerType": "EEventTriggerType::ACTOR",
        "TriggerID": "Mercado_MBR_Girl_01_L3",
        "EventPriority": 0,
        "ProgressLower": 0,
        "ProgressUpper": 30,
        "StartFlagName1": "None",
        "IsTrueCondition1": false,
        "IsAndOperation": false,
        "StartFlagName2": "None",
        "IsTrueCondition2": false,
        "ScenarioProgress": 0
      },
      "EVENT_Mercado_Mercado_MBR_Merchant_02_L3_0": {
        "SelfId": "EVENT_Mercado_Mercado_MBR_Merchant_02_L3_0",
        "EventID": "Mercado_BattleRoad_SUB_0_ACTOR_0410_010",
        "TriggerType": "EEventTriggerType::ACTOR",
        "TriggerID": "Mercado_MBR_Merchant_02_L3",
        "EventPriority": 0,
        "ProgressLower": 0,
        "ProgressUpper": 30,
        "StartFlagName1": "None",
        "IsTrueCondition1": false,
        "IsAndOperation": false,
        "StartFlagName2": "None",
        "IsTrueCondition2": false,
        "ScenarioProgress": 0
      },
      "EVENT_Mercado_Mercado_MBR_OldMan_01_L3_0": {
        "SelfId": "EVENT_Mercado_Mercado_MBR_OldMan_01_L3_0",
        "EventID": "Mercado_BattleRoad_SUB_0_ACTOR_0510_010",
        "TriggerType": "EEventTriggerType::ACTOR",
        "TriggerID": "Mercado_MBR_OldMan_01_L3",
        "EventPriority": 0,
        "ProgressLower": 0,
        "ProgressUpper": 30,
        "StartFlagName1": "None",
        "IsTrueCondition1": false,
        "IsAndOperation": false,
        "StartFlagName2": "None",
        "IsTrueCondition2": false,
        "ScenarioProgress": 0
      },
      "EVENT_Mercado_Mercado_MBR_Woman_01_L3_0": {
        "SelfId": "EVENT_Mercado_Mercado_MBR_Woman_01_L3_0",
        "EventID": "Mercado_BattleRoad_SUB_0_ACTOR_0610_010",
        "TriggerType": "EEventTriggerType::ACTOR",
        "TriggerID": "Mercado_MBR_Woman_01_L3",
        "EventPriority": 0,
        "ProgressLower": 0,
        "ProgressUpper": 30,
        "StartFlagName1": "None",
        "IsTrueCondition1": false,
        "IsAndOperation": false,
        "StartFlagName2": "None",
        "IsTrueCondition2": false,
        "ScenarioProgress": 0
      }
    }
  }
]